MANIFEST.in
README.rst
requirements.txt
setup.cfg
setup.py
version.py
yahoo_oauth/__init__.py
yahoo_oauth/logger.py
yahoo_oauth/oauth.py
yahoo_oauth/utils.py
yahoo_oauth.egg-info/PKG-INFO
yahoo_oauth.egg-info/SOURCES.txt
yahoo_oauth.egg-info/dependency_links.txt
yahoo_oauth.egg-info/requires.txt
yahoo_oauth.egg-info/top_level.txt