Metadata-Version: 1.1
Name: yahoo-oauth
Version: 1.1
Summary: Python Yahoo OAuth Library. Supports OAuth1 and OAuth2
Home-page: https://github.com/josuebrunel/yahoo-oauth
Author: Josue Kouka
Author-email: josuebrunel@gmail.com
License: MIT
Download-URL: https://github.com/josuebrunel/yahoo-oauth/archive/1.1.tar.gz
Keywords: yahoo,oauth,oauth1,oauth2
Platform: Any
Classifier: Programming Language :: Python
Classifier: Programming Language :: Python :: 2
Classifier: Programming Language :: Python :: 3
Classifier: Programming Language :: Python :: Implementation :: CPython
Classifier: Programming Language :: Python :: Implementation :: PyPy
Classifier: Development Status :: 5 - Production/Stable
Classifier: Topic :: Software Development :: Libraries :: Python Modules
Classifier: Environment :: Console
Classifier: Intended Audience :: Developers
Classifier: License :: OSI Approved :: MIT License
